ml4t/backtest/AGENT.md
ml4t/backtest/__init__.py
ml4t/backtest/_version.py
ml4t/backtest/analysis.py
ml4t/backtest/broker.py
ml4t/backtest/calendar.py
ml4t/backtest/config.py
ml4t/backtest/datafeed.py
ml4t/backtest/engine.py
ml4t/backtest/export.py
ml4t/backtest/models.py
ml4t/backtest/result.py
ml4t/backtest/sessions.py
ml4t/backtest/strategy.py
ml4t/backtest/types.py
ml4t/backtest/accounting/AGENT.md
ml4t/backtest/accounting/__init__.py
ml4t/backtest/accounting/account.py
ml4t/backtest/accounting/gatekeeper.py
ml4t/backtest/accounting/policy.py
ml4t/backtest/analytics/AGENT.md
ml4t/backtest/analytics/__init__.py
ml4t/backtest/analytics/bridge.py
ml4t/backtest/analytics/equity.py
ml4t/backtest/analytics/metrics.py
ml4t/backtest/analytics/trades.py
ml4t/backtest/execution/AGENT.md
ml4t/backtest/execution/__init__.py
ml4t/backtest/execution/fill_executor.py
ml4t/backtest/execution/impact.py
ml4t/backtest/execution/limits.py
ml4t/backtest/execution/rebalancer.py
ml4t/backtest/execution/result.py
ml4t/backtest/presets/backtrader.yaml
ml4t/backtest/presets/default.yaml
ml4t/backtest/presets/realistic.yaml
ml4t/backtest/presets/vectorbt.yaml
ml4t/backtest/presets/zipline.yaml
ml4t/backtest/risk/AGENT.md
ml4t/backtest/risk/__init__.py
ml4t/backtest/risk/types.py
ml4t/backtest/risk/portfolio/AGENT.md
ml4t/backtest/risk/portfolio/__init__.py
ml4t/backtest/risk/portfolio/limits.py
ml4t/backtest/risk/portfolio/manager.py
ml4t/backtest/risk/position/AGENT.md
ml4t/backtest/risk/position/__init__.py
ml4t/backtest/risk/position/composite.py
ml4t/backtest/risk/position/dynamic.py
ml4t/backtest/risk/position/protocol.py
ml4t/backtest/risk/position/signal.py
ml4t/backtest/risk/position/static.py
ml4t/backtest/strategies/AGENT.md
ml4t/backtest/strategies/__init__.py
ml4t/backtest/strategies/templates.py
ml4t_backtest-0.1.0a5.dist-info/METADATA
ml4t_backtest-0.1.0a5.dist-info/WHEEL
ml4t_backtest-0.1.0a5.dist-info/RECORD
