Metadata-Version: 2.4
Name: ml4t-backtest
Version: 0.1.0a5
Summary: State-of-the-art event-driven backtesting engine for quantitative trading
Project-URL: Homepage, https://github.com/ml4t/ml4t-backtest
Project-URL: Documentation, https://ml4t-backtest.readthedocs.io
Project-URL: Repository, https://github.com/ml4t/ml4t-backtest
Project-URL: Issues, https://github.com/ml4t/ml4t-backtest/issues
Project-URL: Changelog, https://github.com/ml4t/ml4t-backtest/blob/main/CHANGELOG.md
Author-email: QuantLab Team <info@quantlab.io>
Maintainer-email: QuantLab Contributors <dev@quantlab.io>
License: MIT
Keywords: algorithmic-trading,backtesting,event-driven,execution,finance,polars,portfolio,quantitative-finance,risk-management,simulation,trading
Classifier: Development Status :: 4 - Beta
Classifier: Intended Audience :: Developers
Classifier: Intended Audience :: Financial and Insurance Industry
Classifier: Intended Audience :: Science/Research
Classifier: License :: OSI Approved :: MIT License
Classifier: Operating System :: OS Independent
Classifier: Programming Language :: Python :: 3
Classifier: Programming Language :: Python :: 3.11
Classifier: Programming Language :: Python :: 3.12
Classifier: Programming Language :: Python :: 3.13
Classifier: Topic :: Office/Business :: Financial :: Investment
Classifier: Topic :: Scientific/Engineering :: Information Analysis
Classifier: Topic :: Software Development :: Libraries :: Application Frameworks
Classifier: Typing :: Typed
Requires-Python: >=3.11
Requires-Dist: numba>=0.57.0
Requires-Dist: numpy>=1.24.0
Requires-Dist: pandas-market-calendars>=4.0.0
Requires-Dist: pandas>=2.0.0
Requires-Dist: polars>=0.20.0
Requires-Dist: pyarrow>=14.0.0
Requires-Dist: pydantic<3.0.0,>=1.10.0
Requires-Dist: python-dateutil>=2.8.0
Requires-Dist: pyyaml>=6.0.0
Requires-Dist: sortedcontainers>=2.4.0
Requires-Dist: structlog>=23.0.0
Requires-Dist: tables>=3.8.0
Provides-Extra: advanced
Requires-Dist: cvxpy>=1.3.0; extra == 'advanced'
Requires-Dist: networkx>=3.0; extra == 'advanced'
Provides-Extra: all
Requires-Dist: cvxpy>=1.3.0; extra == 'all'
Requires-Dist: dash>=2.11.0; extra == 'all'
Requires-Dist: hypothesis>=6.80.0; extra == 'all'
Requires-Dist: ipdb>=0.13.0; extra == 'all'
Requires-Dist: ipython>=8.14.0; extra == 'all'
Requires-Dist: matplotlib>=3.7.0; extra == 'all'
Requires-Dist: mypy>=1.5.0; extra == 'all'
Requires-Dist: myst-parser>=2.0.0; extra == 'all'
Requires-Dist: nbsphinx>=0.9.0; extra == 'all'
Requires-Dist: networkx>=3.0; extra == 'all'
Requires-Dist: plotly>=5.15.0; extra == 'all'
Requires-Dist: pre-commit>=3.3.0; extra == 'all'
Requires-Dist: pytest-asyncio>=0.21.0; extra == 'all'
Requires-Dist: pytest-benchmark>=4.0.0; extra == 'all'
Requires-Dist: pytest-cov>=4.1.0; extra == 'all'
Requires-Dist: pytest-timeout>=2.1.0; extra == 'all'
Requires-Dist: pytest-xdist>=3.3.0; extra == 'all'
Requires-Dist: pytest>=7.4.0; extra == 'all'
Requires-Dist: ruff>=0.1.0; extra == 'all'
Requires-Dist: sphinx-autodoc-typehints>=1.24.0; extra == 'all'
Requires-Dist: sphinx-rtd-theme>=1.3.0; extra == 'all'
Requires-Dist: sphinx>=7.0.0; extra == 'all'
Provides-Extra: comparison
Requires-Dist: backtrader>=1.9.0; extra == 'comparison'
Requires-Dist: vectorbt>=0.24.0; extra == 'comparison'
Requires-Dist: zipline-reloaded>=2.4.0; extra == 'comparison'
Provides-Extra: dev
Requires-Dist: hypothesis>=6.80.0; extra == 'dev'
Requires-Dist: ipdb>=0.13.0; extra == 'dev'
Requires-Dist: ipython>=8.14.0; extra == 'dev'
Requires-Dist: mypy>=1.5.0; extra == 'dev'
Requires-Dist: pre-commit>=3.3.0; extra == 'dev'
Requires-Dist: pytest-asyncio>=0.21.0; extra == 'dev'
Requires-Dist: pytest-benchmark>=4.0.0; extra == 'dev'
Requires-Dist: pytest-cov>=4.1.0; extra == 'dev'
Requires-Dist: pytest-timeout>=2.1.0; extra == 'dev'
Requires-Dist: pytest-xdist>=3.3.0; extra == 'dev'
Requires-Dist: pytest>=7.4.0; extra == 'dev'
Requires-Dist: ruff>=0.1.0; extra == 'dev'
Provides-Extra: docs
Requires-Dist: myst-parser>=2.0.0; extra == 'docs'
Requires-Dist: nbsphinx>=0.9.0; extra == 'docs'
Requires-Dist: sphinx-autodoc-typehints>=1.24.0; extra == 'docs'
Requires-Dist: sphinx-rtd-theme>=1.3.0; extra == 'docs'
Requires-Dist: sphinx>=7.0.0; extra == 'docs'
Provides-Extra: viz
Requires-Dist: dash>=2.11.0; extra == 'viz'
Requires-Dist: matplotlib>=3.7.0; extra == 'viz'
Requires-Dist: plotly>=5.15.0; extra == 'viz'
